{"H1":
 {"standing":
  {"8":
   {"place":1,"name":"Sloep VC 1","organisation_id":1694,"matches":22,"score":64,"counterscore":18,"forfait":0,"points":60,"score_diff":46,"wins":21,"loss":1,"score_divided":"3,56","ties":0,"custom_results":{"3\/0":9,"3\/1":9,"3\/2":3,"2\/3":0,"1\/3":1,"0\/3":0}},
   "11":{"place":2,"name":"VCK","organisation_id":1700,"matches":22,"score":51,"counterscore":33,"forfait":0,"points":45,"score_diff":18,"wins":16,"loss":6,"score_divided":"1,55","ties":0,"custom_results":{"3\/0":4,"3\/1":9,"3\/2":3,"2\/3":0,"1\/3":3,"0\/3":3}},
   "6":{"place":3,"name":"Mentha","organisation_id":1678,"matches":22,"score":53,"counterscore":29,"forfait":0,"points":45,"score_diff":24,"wins":15,"loss":7,"score_divided":"1,83","ties":0,"custom_results":{"3\/0":9,"3\/1":4,"3\/2":2,"2\/3":2,"1\/3":4,"0\/3":1}},
   "7":{"place":4,"name":"Oxaco BVC Antw 1","organisation_id":1687,"matches":22,"score":53,"counterscore":37,"forfait":0,"points":43,"score_diff":16,"wins":15,"loss":7,"score_divided":"1,43","ties":0,"custom_results":{"3\/0":3,"3\/1":8,"3\/2":4,"2\/3":2,"1\/3":4,"0\/3":1}},
   "10":{"place":5,"name":"TESLA Lint VC 2","organisation_id":1703,"matches":22,"score":49,"counterscore":39,"forfait":0,"points":39,"score_diff":10,"wins":12,"loss":10,"score_divided":"1,26","ties":0,"custom_results":{"3\/0":4,"3\/1":7,"3\/2":1,"2\/3":4,"1\/3":5,"0\/3":1}},
   "5":{"place":6,"name":"Meilsen VC","organisation_id":1565,"matches":22,"score":43,"counterscore":43,"forfait":0,"points":35,"score_diff":0,"wins":12,"loss":10,"score_divided":"1,00","ties":0,"custom_results":{"3\/0":2,"3\/1":7,"3\/2":3,"2\/3":2,"1\/3":3,"0\/3":5}},
   "3":{"place":7,"name":"Kokaz 1","organisation_id":1673,"matches":22,"score":49,"counterscore":44,"forfait":0,"points":35,"score_diff":5,"wins":11,"loss":11,"score_divided":"1,11","ties":0,"custom_results":{"3\/0":4,"3\/1":3,"3\/2":4,"2\/3":6,"1\/3":4,"0\/3":1}},
   "1":{"place":8,"name":"Ampersand","organisation_id":1650,"matches":22,"score":38,"counterscore":51,"forfait":0,"points":25,"score_diff":-13,"wins":9,"loss":13,"score_divided":"0,75","ties":0,"custom_results":{"3\/0":2,"3\/1":2,"3\/2":5,"2\/3":3,"1\/3":5,"0\/3":5}},
   "4":{"place":9,"name":"Komart 1","organisation_id":1674,"matches":22,"score":39,"counterscore":52,"forfait":0,"points":25,"score_diff":-13,"wins":8,"loss":14,"score_divided":"0,75","ties":0,"custom_results":{"3\/0":1,"3\/1":4,"3\/2":3,"2\/3":4,"1\/3":7,"0\/3":3}},
   "2":{"place":10,"name":"Kessel.be","organisation_id":1672,"matches":22,"score":34,"counterscore":50,"forfait":0,"points":22,"score_diff":-16,"wins":8,"loss":14,"score_divided":"0,68","ties":0,"custom_results":{"3\/0":2,"3\/1":4,"3\/2":2,"2\/3":0,"1\/3":10,"0\/3":4}},
   "9":{"place":11,"name":"TESLA Lint VC 1","organisation_id":1703,"matches":22,"score":31,"counterscore":61,"forfait":0,"points":15,"score_diff":-30,"wins":3,"loss":19,"score_divided":"0,51","ties":0,"custom_results":{"3\/0":1,"3\/1":0,"3\/2":2,"2\/3":8,"1\/3":6,"0\/3":5}},
   "12":{"place":12,"name":"VP Gaverland","organisation_id":1569,"matches":22,"score":15,"counterscore":62,"forfait":0,"points":7,"score_diff":-47,"wins":2,"loss":20,"score_divided":"0,24","ties":0,"custom_results":{"3\/0":1,"3\/1":0,"3\/2":1,"2\/3":2,"1\/3":5,"0\/3":13}}},
  "name":"HEREN 1","type":"league"},
 "H2":{"standing":{"16":{"place":1,"name":"Herenthout","organisation_id":2195,"matches":22,"score":65,"counterscore":13,"forfait":0,"points":63,"score_diff":52,"wins":21,"loss":1,"score_divided":"5,00","ties":0,"custom_results":{"3\/0":12,"3\/1":8,"3\/2":1,"2\/3":1,"1\/3":0,"0\/3":0}},"17":{"place":2,"name":"Jong Edegem 1","organisation_id":1670,"matches":22,"score":50,"counterscore":36,"forfait":0,"points":41,"score_diff":14,"wins":13,"loss":9,"score_divided":"1,39","ties":0,"custom_results":{"3\/0":6,"3\/1":5,"3\/2":2,"2\/3":4,"1\/3":3,"0\/3":2}},"22":{"place":3,"name":"Vosco 1","organisation_id":1706,"matches":22,"score":49,"counterscore":37,"forfait":1,"points":38,"score_diff":12,"wins":13,"loss":9,"score_divided":"1,32","ties":0,"custom_results":{"3\/0":6,"3\/1":4,"3\/2":3,"2\/3":3,"1\/3":4,"0\/3":2}},"15":{"place":4,"name":"Duvo","organisation_id":1665,"matches":22,"score":48,"counterscore":41,"forfait":0,"points":38,"score_diff":7,"wins":13,"loss":9,"score_divided":"1,17","ties":0,"custom_results":{"3\/0":3,"3\/1":6,"3\/2":4,"2\/3":3,"1\/3":3,"0\/3":3}},"20":{"place":5,"name":"t Konifair","organisation_id":1851,"matches":22,"score":43,"counterscore":43,"forfait":1,"points":32,"score_diff":0,"wins":11,"loss":11,"score_divided":"1,00","ties":0,"custom_results":{"3\/0":4,"3\/1":4,"3\/2":3,"2\/3":3,"1\/3":4,"0\/3":4}},"14":{"place":6,"name":"Blokkeer Zandhoven","organisation_id":1655,"matches":22,"score":43,"counterscore":44,"forfait":0,"points":32,"score_diff":-1,"wins":11,"loss":11,"score_divided":"0,98","ties":0,"custom_results":{"3\/0":4,"3\/1":3,"3\/2":4,"2\/3":3,"1\/3":4,"0\/3":4}},"23":{"place":7,"name":"WEK Loenhout","organisation_id":1708,"matches":22,"score":39,"counterscore":46,"forfait":0,"points":31,"score_diff":-7,"wins":11,"loss":11,"score_divided":"0,85","ties":0,"custom_results":{"3\/0":1,"3\/1":7,"3\/2":3,"2\/3":1,"1\/3":4,"0\/3":6}},"18":{"place":8,"name":"Smash Lier","organisation_id":1739,"matches":22,"score":36,"counterscore":51,"forfait":0,"points":26,"score_diff":-15,"wins":9,"loss":13,"score_divided":"0,71","ties":0,"custom_results":{"3\/0":1,"3\/1":4,"3\/2":4,"2\/3":3,"1\/3":3,"0\/3":7}},"24":{"place":9,"name":"Woka 1","organisation_id":1709,"matches":22,"score":39,"counterscore":48,"forfait":0,"points":26,"score_diff":-9,"wins":8,"loss":14,"score_divided":"0,81","ties":0,"custom_results":{"3\/0":3,"3\/1":4,"3\/2":1,"2\/3":3,"1\/3":9,"0\/3":2}},"19":{"place":10,"name":"Sveka Schoten 1","organisation_id":1696,"matches":22,"score":37,"counterscore":49,"forfait":0,"points":25,"score_diff":-12,"wins":7,"loss":15,"score_divided":"0,76","ties":0,"custom_results":{"3\/0":4,"3\/1":2,"3\/2":1,"2\/3":5,"1\/3":6,"0\/3":4}},"21":{"place":11,"name":"TESLA Lint VC 3","organisation_id":1703,"matches":22,"score":33,"counterscore":51,"forfait":0,"points":24,"score_diff":-18,"wins":9,"loss":13,"score_divided":"0,65","ties":0,"custom_results":{"3\/0":1,"3\/1":4,"3\/2":4,"2\/3":1,"1\/3":4,"0\/3":8}},"13":{"place":12,"name":"Antenna Ukraine","organisation_id":1651,"matches":22,"score":32,"counterscore":55,"forfait":0,"points":18,"score_diff":-23,"wins":6,"loss":16,"score_divided":"0,58","ties":0,"custom_results":{"3\/0":2,"3\/1":1,"3\/2":3,"2\/3":3,"1\/3":8,"0\/3":5}}},"name":"HEREN 2","type":"league"},"H3a":{"standing":{"33":{"place":1,"name":"TESLA Lint VC 4","organisation_id":1703,"matches":20,"score":57,"counterscore":10,"forfait":0,"points":56,"score_diff":47,"wins":19,"loss":1,"score_divided":"5,70","ties":0,"custom_results":{"3\/0":13,"3\/1":5,"3\/2":1,"2\/3":0,"1\/3":0,"0\/3":1}},"29":{"place":2,"name":"OV Dennenbad","organisation_id":1685,"matches":20,"score":51,"counterscore":17,"forfait":0,"points":48,"score_diff":34,"wins":16,"loss":4,"score_divided":"3,00","ties":0,"custom_results":{"3\/0":12,"3\/1":3,"3\/2":1,"2\/3":1,"1\/3":1,"0\/3":2}},"27":{"place":3,"name":"Geel-Zwart Wijnegem 1","organisation_id":1664,"matches":20,"score":50,"counterscore":25,"forfait":0,"points":45,"score_diff":25,"wins":15,"loss":5,"score_divided":"2,00","ties":0,"custom_results":{"3\/0":6,"3\/1":8,"3\/2":1,"2\/3":1,"1\/3":3,"0\/3":1}},"28":{"place":4,"name":"Kokaz 2","organisation_id":1673,"matches":20,"score":47,"counterscore":24,"forfait":0,"points":41,"score_diff":23,"wins":14,"loss":6,"score_divided":"1,96","ties":0,"custom_results":{"3\/0":10,"3\/1":2,"3\/2":2,"2\/3":1,"1\/3":3,"0\/3":2}},"25":{"place":5,"name":"Bravoc Ranst 1","organisation_id":1659,"matches":20,"score":43,"counterscore":36,"forfait":0,"points":35,"score_diff":7,"wins":11,"loss":9,"score_divided":"1,19","ties":0,"custom_results":{"3\/0":3,"3\/1":7,"3\/2":1,"2\/3":3,"1\/3":4,"0\/3":2}},"26":{"place":6,"name":"Dosko@Ristorno 1","organisation_id":1662,"matches":20,"score":32,"counterscore":41,"forfait":0,"points":26,"score_diff":-9,"wins":10,"loss":10,"score_divided":"0,78","ties":0,"custom_results":{"3\/0":3,"3\/1":3,"3\/2":4,"2\/3":0,"1\/3":2,"0\/3":8}},"35":{"place":7,"name":"Volmar Ekeren","organisation_id":1855,"matches":20,"score":31,"counterscore":45,"forfait":0,"points":24,"score_diff":-14,"wins":7,"loss":13,"score_divided":"0,69","ties":0,"custom_results":{"3\/0":2,"3\/1":4,"3\/2":1,"2\/3":4,"1\/3":2,"0\/3":7}},"34":{"place":8,"name":"Vojaka 1","organisation_id":1702,"matches":20,"score":24,"counterscore":48,"forfait":0,"points":15,"score_diff":-24,"wins":5,"loss":15,"score_divided":"0,50","ties":0,"custom_results":{"3\/0":3,"3\/1":1,"3\/2":1,"2\/3":1,"1\/3":7,"0\/3":7}},"31":{"place":9,"name":"Sveka Schoten 2","organisation_id":1696,"matches":20,"score":25,"counterscore":51,"forfait":0,"points":15,"score_diff":-26,"wins":4,"loss":16,"score_divided":"0,49","ties":0,"custom_results":{"3\/0":1,"3\/1":3,"3\/2":0,"2\/3":3,"1\/3":7,"0\/3":6}},"30":{"place":10,"name":"Sloep VC 2","organisation_id":1694,"matches":20,"score":23,"counterscore":52,"forfait":0,"points":14,"score_diff":-29,"wins":6,"loss":14,"score_divided":"0,44","ties":0,"custom_results":{"3\/0":0,"3\/1":2,"3\/2":4,"2\/3":0,"1\/3":5,"0\/3":9}},"32":{"place":11,"name":"t Pleintje","organisation_id":1697,"matches":20,"score":20,"counterscore":54,"forfait":0,"points":11,"score_diff":-34,"wins":3,"loss":17,"score_divided":"0,37","ties":0,"custom_results":{"3\/0":1,"3\/1":1,"3\/2":1,"2\/3":3,"1\/3":5,"0\/3":9}}},"name":"HEREN 3A","type":"league"},"H3B":{"standing":{"46":{"place":1,"name":"Woka 2","organisation_id":1709,"matches":20,"score":55,"counterscore":19,"forfait":0,"points":51,"score_diff":36,"wins":17,"loss":3,"score_divided":"2,89","ties":0,"custom_results":{"3\/0":9,"3\/1":6,"3\/2":2,"2\/3":2,"1\/3":0,"0\/3":1}},"42":{"place":2,"name":"Osta Berchem 1","organisation_id":1684,"matches":20,"score":50,"counterscore":35,"forfait":0,"points":39,"score_diff":15,"wins":14,"loss":6,"score_divided":"1,43","ties":0,"custom_results":{"3\/0":3,"3\/1":5,"3\/2":6,"2\/3":3,"1\/3":2,"0\/3":1}},"38":{"place":3,"name":"Kokaz 3","organisation_id":1673,"matches":20,"score":41,"counterscore":36,"forfait":0,"points":33,"score_diff":5,"wins":11,"loss":9,"score_divided":"1,14","ties":0,"custom_results":{"3\/0":4,"3\/1":5,"3\/2":2,"2\/3":2,"1\/3":4,"0\/3":3}},"41":{"place":4,"name":"Mortsel Volley Antw","organisation_id":1680,"matches":20,"score":41,"counterscore":39,"forfait":0,"points":30,"score_diff":2,"wins":11,"loss":9,"score_divided":"1,05","ties":0,"custom_results":{"3\/0":4,"3\/1":2,"3\/2":5,"2\/3":2,"1\/3":4,"0\/3":3}},"40":{"place":5,"name":"Mavoc Mechelen","organisation_id":1677,"matches":20,"score":36,"counterscore":39,"forfait":0,"points":29,"score_diff":-3,"wins":10,"loss":10,"score_divided":"0,92","ties":0,"custom_results":{"3\/0":4,"3\/1":3,"3\/2":3,"2\/3":2,"1\/3":2,"0\/3":6}},"43":{"place":6,"name":"Oxaco BVC Antw 2","organisation_id":1687,"matches":20,"score":36,"counterscore":36,"forfait":1,"points":29,"score_diff":0,"wins":9,"loss":11,"score_divided":"1,00","ties":0,"custom_results":{"3\/0":7,"3\/1":1,"3\/2":1,"2\/3":4,"1\/3":1,"0\/3":6}},"36":{"place":7,"name":"Joledi 1","organisation_id":1669,"matches":20,"score":37,"counterscore":41,"forfait":0,"points":28,"score_diff":-4,"wins":9,"loss":11,"score_divided":"0,90","ties":0,"custom_results":{"3\/0":3,"3\/1":4,"3\/2":2,"2\/3":3,"1\/3":4,"0\/3":4}},"37":{"place":8,"name":"Jong Edegem 2","organisation_id":1670,"matches":20,"score":36,"counterscore":43,"forfait":0,"points":25,"score_diff":-7,"wins":8,"loss":12,"score_divided":"0,84","ties":0,"custom_results":{"3\/0":3,"3\/1":3,"3\/2":2,"2\/3":3,"1\/3":6,"0\/3":3}},"45":{"place":9,"name":"TESLA Lint VC 5","organisation_id":1703,"matches":20,"score":37,"counterscore":45,"forfait":0,"points":25,"score_diff":-8,"wins":8,"loss":12,"score_divided":"0,82","ties":0,"custom_results":{"3\/0":2,"3\/1":3,"3\/2":3,"2\/3":4,"1\/3":5,"0\/3":3}},"39":{"place":10,"name":"Komart 2","organisation_id":1674,"matches":20,"score":37,"counterscore":49,"forfait":0,"points":22,"score_diff":-12,"wins":8,"loss":12,"score_divided":"0,76","ties":0,"custom_results":{"3\/0":0,"3\/1":3,"3\/2":5,"2\/3":3,"1\/3":7,"0\/3":2}},"44":{"place":11,"name":"Pannenhuiseke VK 1","organisation_id":1846,"matches":20,"score":25,"counterscore":49,"forfait":1,"points":17,"score_diff":-24,"wins":5,"loss":15,"score_divided":"0,51","ties":0,"custom_results":{"3\/0":2,"3\/1":2,"3\/2":1,"2\/3":4,"1\/3":2,"0\/3":9}}},"name":"HEREN 3B","type":"league"},"H4A":{"standing":{"51":{"place":1,"name":"Pannenhuiseke VK 2","organisation_id":1846,"matches":18,"score":53,"counterscore":10,"forfait":0,"points":51,"score_diff":43,"wins":17,"loss":1,"score_divided":"5,30","ties":0,"custom_results":{"3\/0":11,"3\/1":5,"3\/2":1,"2\/3":1,"1\/3":0,"0\/3":0}},"49":{"place":2,"name":"Osta Berchem 2","organisation_id":1684,"matches":18,"score":51,"counterscore":10,"forfait":0,"points":49,"score_diff":41,"wins":17,"loss":1,"score_divided":"5,10","ties":0,"custom_results":{"3\/0":12,"3\/1":3,"3\/2":2,"2\/3":0,"1\/3":0,"0\/3":1}},"55":{"place":3,"name":"Vosco 2","organisation_id":1706,"matches":18,"score":40,"counterscore":20,"forfait":0,"points":38,"score_diff":20,"wins":13,"loss":5,"score_divided":"2,00","ties":0,"custom_results":{"3\/0":9,"3\/1":3,"3\/2":1,"2\/3":0,"1\/3":1,"0\/3":4}},"50":{"place":4,"name":"Oxaco BVC Antw 3","organisation_id":1687,"matches":18,"score":39,"counterscore":28,"forfait":0,"points":33,"score_diff":11,"wins":10,"loss":8,"score_divided":"1,39","ties":0,"custom_results":{"3\/0":7,"3\/1":2,"3\/2":1,"2\/3":4,"1\/3":1,"0\/3":3}},"48":{"place":5,"name":"Dosko@Ristorno 2","organisation_id":1662,"matches":18,"score":33,"counterscore":31,"forfait":1,"points":30,"score_diff":2,"wins":11,"loss":7,"score_divided":"1,06","ties":0,"custom_results":{"3\/0":3,"3\/1":6,"3\/2":2,"2\/3":0,"1\/3":0,"0\/3":7}},"52":{"place":6,"name":"Patria","organisation_id":1688,"matches":18,"score":24,"counterscore":37,"forfait":1,"points":17,"score_diff":-13,"wins":6,"loss":12,"score_divided":"0,65","ties":0,"custom_results":{"3\/0":5,"3\/1":1,"3\/2":0,"2\/3":0,"1\/3":6,"0\/3":6}},"47":{"place":7,"name":"Don Bosco Hoboken VC","organisation_id":1661,"matches":18,"score":23,"counterscore":39,"forfait":0,"points":17,"score_diff":-16,"wins":6,"loss":12,"score_divided":"0,59","ties":0,"custom_results":{"3\/0":4,"3\/1":1,"3\/2":1,"2\/3":0,"1\/3":5,"0\/3":7}},"54":{"place":8,"name":"Vojaka 2","organisation_id":1702,"matches":18,"score":21,"counterscore":44,"forfait":0,"points":16,"score_diff":-23,"wins":5,"loss":13,"score_divided":"0,48","ties":0,"custom_results":{"3\/0":1,"3\/1":3,"3\/2":1,"2\/3":2,"1\/3":2,"0\/3":9}},"53":{"place":9,"name":"TESLA Lint VC 6","organisation_id":1703,"matches":18,"score":17,"counterscore":49,"forfait":0,"points":9,"score_diff":-32,"wins":3,"loss":15,"score_divided":"0,35","ties":0,"custom_results":{"3\/0":0,"3\/1":2,"3\/2":1,"2\/3":1,"1\/3":6,"0\/3":8}},"56":{"place":10,"name":"Woka 3","organisation_id":1709,"matches":18,"score":17,"counterscore":50,"forfait":0,"points":8,"score_diff":-33,"wins":2,"loss":16,"score_divided":"0,34","ties":0,"custom_results":{"3\/0":0,"3\/1":2,"3\/2":0,"2\/3":2,"1\/3":7,"0\/3":7}}},"name":"HEREN 4A","type":"league"},"H4B":{"standing":{"60":{"place":1,"name":"Geel-Zwart Wijnegem 2","organisation_id":1664,"matches":18,"score":54,"counterscore":7,"forfait":0,"points":54,"score_diff":47,"wins":18,"loss":0,"score_divided":"7,71","ties":0,"custom_results":{"3\/0":11,"3\/1":7,"3\/2":0,"2\/3":0,"1\/3":0,"0\/3":0}},"57":{"place":2,"name":"Bravoc Ranst 2","organisation_id":1659,"matches":18,"score":44,"counterscore":23,"forfait":0,"points":38,"score_diff":21,"wins":13,"loss":5,"score_divided":"1,91","ties":0,"custom_results":{"3\/0":7,"3\/1":4,"3\/2":2,"2\/3":1,"1\/3":3,"0\/3":1}},"65":{"place":3,"name":"TESLA Lint VC 7","organisation_id":1703,"matches":18,"score":44,"counterscore":26,"forfait":0,"points":38,"score_diff":18,"wins":12,"loss":6,"score_divided":"1,69","ties":0,"custom_results":{"3\/0":5,"3\/1":6,"3\/2":1,"2\/3":3,"1\/3":2,"0\/3":1}},"66":{"place":4,"name":"Vosco 3","organisation_id":1706,"matches":18,"score":40,"counterscore":26,"forfait":0,"points":34,"score_diff":14,"wins":12,"loss":6,"score_divided":"1,54","ties":0,"custom_results":{"3\/0":6,"3\/1":4,"3\/2":2,"2\/3":0,"1\/3":4,"0\/3":2}},"61":{"place":5,"name":"Hellvoc","organisation_id":1691,"matches":18,"score":31,"counterscore":39,"forfait":0,"points":24,"score_diff":-8,"wins":9,"loss":9,"score_divided":"0,79","ties":0,"custom_results":{"3\/0":1,"3\/1":4,"3\/2":4,"2\/3":1,"1\/3":2,"0\/3":6}},"58":{"place":6,"name":"Cantincrode","organisation_id":1660,"matches":18,"score":30,"counterscore":37,"forfait":0,"points":23,"score_diff":-7,"wins":7,"loss":11,"score_divided":"0,81","ties":0,"custom_results":{"3\/0":3,"3\/1":4,"3\/2":0,"2\/3":2,"1\/3":5,"0\/3":4}},"63":{"place":7,"name":"Kokaz 4","organisation_id":1673,"matches":18,"score":26,"counterscore":40,"forfait":0,"points":20,"score_diff":-14,"wins":7,"loss":11,"score_divided":"0,65","ties":0,"custom_results":{"3\/0":1,"3\/1":5,"3\/2":1,"2\/3":0,"1\/3":5,"0\/3":6}},"64":{"place":8,"name":"Komart 3","organisation_id":1674,"matches":18,"score":29,"counterscore":38,"forfait":0,"points":20,"score_diff":-9,"wins":6,"loss":12,"score_divided":"0,76","ties":0,"custom_results":{"3\/0":4,"3\/1":2,"3\/2":0,"2\/3":2,"1\/3":7,"0\/3":3}},"59":{"place":9,"name":"Den Doedelzak VC","organisation_id":2198,"matches":18,"score":23,"counterscore":40,"forfait":2,"points":15,"score_diff":-17,"wins":6,"loss":12,"score_divided":"0,58","ties":0,"custom_results":{"3\/0":3,"3\/1":2,"3\/2":1,"2\/3":0,"1\/3":5,"0\/3":7}},"62":{"place":10,"name":"Joledi 2","organisation_id":1669,"matches":18,"score":9,"counterscore":54,"forfait":0,"points":2,"score_diff":-45,"wins":0,"loss":18,"score_divided":"0,17","ties":0,"custom_results":{"3\/0":0,"3\/1":0,"3\/2":0,"2\/3":2,"1\/3":5,"0\/3":11}}},"name":"HEREN 4B","type":"league"},"D1":{"standing":{"78":{"place":1,"name":"Vos Reinaert 1","organisation_id":1568,"matches":22,"score":59,"counterscore":23,"forfait":0,"points":52,"score_diff":36,"wins":17,"loss":5,"score_divided":"2,57","ties":0,"custom_results":{"3\/0":11,"3\/1":4,"3\/2":2,"2\/3":3,"1\/3":2,"0\/3":0}},"67":{"place":2,"name":"Blokkeer Zandhoven","organisation_id":1655,"matches":22,"score":51,"counterscore":30,"forfait":0,"points":44,"score_diff":21,"wins":14,"loss":8,"score_divided":"1,70","ties":0,"custom_results":{"3\/0":9,"3\/1":4,"3\/2":1,"2\/3":3,"1\/3":3,"0\/3":2}},"68":{"place":3,"name":"Dalvo VC","organisation_id":1562,"matches":22,"score":52,"counterscore":37,"forfait":0,"points":43,"score_diff":15,"wins":14,"loss":8,"score_divided":"1,41","ties":0,"custom_results":{"3\/0":4,"3\/1":7,"3\/2":3,"2\/3":4,"1\/3":2,"0\/3":2}},"69":{"place":4,"name":"Een Twee Drei","organisation_id":1563,"matches":22,"score":49,"counterscore":35,"forfait":1,"points":40,"score_diff":14,"wins":14,"loss":8,"score_divided":"1,40","ties":0,"custom_results":{"3\/0":7,"3\/1":3,"3\/2":4,"2\/3":3,"1\/3":1,"0\/3":4}},"71":{"place":5,"name":"Geel-Zwart Wijnegem 1","organisation_id":1664,"matches":22,"score":44,"counterscore":39,"forfait":1,"points":37,"score_diff":5,"wins":13,"loss":9,"score_divided":"1,13","ties":0,"custom_results":{"3\/0":3,"3\/1":8,"3\/2":2,"2\/3":1,"1\/3":3,"0\/3":5}},"74":{"place":6,"name":"RVW","organisation_id":1959,"matches":22,"score":43,"counterscore":43,"forfait":0,"points":33,"score_diff":0,"wins":11,"loss":11,"score_divided":"1,00","ties":0,"custom_results":{"3\/0":4,"3\/1":4,"3\/2":3,"2\/3":3,"1\/3":4,"0\/3":4}},"77":{"place":7,"name":"Vintage Volley Puurs","organisation_id":2080,"matches":22,"score":41,"counterscore":44,"forfait":0,"points":31,"score_diff":-3,"wins":12,"loss":10,"score_divided":"0,93","ties":0,"custom_results":{"3\/0":3,"3\/1":4,"3\/2":5,"2\/3":0,"1\/3":5,"0\/3":5}},"75":{"place":8,"name":"Sloep VC 1","organisation_id":1694,"matches":22,"score":42,"counterscore":50,"forfait":0,"points":29,"score_diff":-8,"wins":10,"loss":12,"score_divided":"0,84","ties":0,"custom_results":{"3\/0":0,"3\/1":6,"3\/2":4,"2\/3":3,"1\/3":6,"0\/3":3}},"73":{"place":9,"name":"Mortsel Volley Antw 1","organisation_id":1680,"matches":22,"score":44,"counterscore":49,"forfait":0,"points":29,"score_diff":-5,"wins":9,"loss":13,"score_divided":"0,90","ties":0,"custom_results":{"3\/0":2,"3\/1":4,"3\/2":3,"2\/3":5,"1\/3":7,"0\/3":1}},"70":{"place":10,"name":"Fixit Wuustwezel 1","organisation_id":1663,"matches":22,"score":34,"counterscore":48,"forfait":1,"points":24,"score_diff":-14,"wins":8,"loss":14,"score_divided":"0,71","ties":0,"custom_results":{"3\/0":3,"3\/1":4,"3\/2":1,"2\/3":2,"1\/3":6,"0\/3":6}},"76":{"place":11,"name":"Vamos","organisation_id":2197,"matches":22,"score":27,"counterscore":53,"forfait":0,"points":19,"score_diff":-26,"wins":6,"loss":16,"score_divided":"0,51","ties":0,"custom_results":{"3\/0":2,"3\/1":3,"3\/2":1,"2\/3":2,"1\/3":5,"0\/3":9}},"72":{"place":12,"name":"Gimme Waasland","organisation_id":1567,"matches":22,"score":20,"counterscore":55,"forfait":0,"points":12,"score_diff":-35,"wins":4,"loss":18,"score_divided":"0,36","ties":0,"custom_results":{"3\/0":3,"3\/1":1,"3\/2":0,"2\/3":0,"1\/3":8,"0\/3":10}}},"name":"DAMES 1","type":"league"},"D2":{"standing":{"89":{"place":1,"name":"Woka 1","organisation_id":1709,"matches":20,"score":60,"counterscore":4,"forfait":0,"points":60,"score_diff":56,"wins":20,"loss":0,"score_divided":"15,00","ties":0,"custom_results":{"3\/0":16,"3\/1":4,"3\/2":0,"2\/3":0,"1\/3":0,"0\/3":0}},"87":{"place":2,"name":"Volmar Ekeren 1","organisation_id":1855,"matches":20,"score":52,"counterscore":18,"forfait":0,"points":49,"score_diff":34,"wins":16,"loss":4,"score_divided":"2,89","ties":0,"custom_results":{"3\/0":10,"3\/1":6,"3\/2":0,"2\/3":1,"1\/3":2,"0\/3":1}},"83":{"place":3,"name":"Sveka Schoten 2","organisation_id":1696,"matches":20,"score":43,"counterscore":27,"forfait":0,"points":38,"score_diff":16,"wins":13,"loss":7,"score_divided":"1,59","ties":0,"custom_results":{"3\/0":9,"3\/1":2,"3\/2":2,"2\/3":1,"1\/3":2,"0\/3":4}},"88":{"place":4,"name":"Vosco 1","organisation_id":1706,"matches":20,"score":42,"counterscore":31,"forfait":0,"points":34,"score_diff":11,"wins":11,"loss":9,"score_divided":"1,35","ties":0,"custom_results":{"3\/0":8,"3\/1":2,"3\/2":1,"2\/3":2,"1\/3":5,"0\/3":2}},"80":{"place":5,"name":"Kokaz 1","organisation_id":1673,"matches":20,"score":38,"counterscore":42,"forfait":0,"points":30,"score_diff":-4,"wins":10,"loss":10,"score_divided":"0,90","ties":0,"custom_results":{"3\/0":1,"3\/1":6,"3\/2":3,"2\/3":3,"1\/3":2,"0\/3":5}},"84":{"place":6,"name":"Temse VT","organisation_id":2283,"matches":20,"score":37,"counterscore":44,"forfait":0,"points":25,"score_diff":-7,"wins":9,"loss":11,"score_divided":"0,84","ties":0,"custom_results":{"3\/0":2,"3\/1":3,"3\/2":4,"2\/3":2,"1\/3":6,"0\/3":3}},"82":{"place":7,"name":"Sveka Schoten 1","organisation_id":1696,"matches":20,"score":32,"counterscore":41,"forfait":0,"points":25,"score_diff":-9,"wins":9,"loss":11,"score_divided":"0,78","ties":0,"custom_results":{"3\/0":3,"3\/1":4,"3\/2":2,"2\/3":0,"1\/3":5,"0\/3":6}},"79":{"place":8,"name":"Beveren VC","organisation_id":1978,"matches":20,"score":32,"counterscore":43,"forfait":0,"points":25,"score_diff":-11,"wins":8,"loss":12,"score_divided":"0,74","ties":0,"custom_results":{"3\/0":2,"3\/1":5,"3\/2":1,"2\/3":2,"1\/3":4,"0\/3":6}},"81":{"place":9,"name":"Meteoor","organisation_id":1679,"matches":20,"score":29,"counterscore":45,"forfait":0,"points":23,"score_diff":-16,"wins":8,"loss":12,"score_divided":"0,64","ties":0,"custom_results":{"3\/0":1,"3\/1":5,"3\/2":2,"2\/3":1,"1\/3":3,"0\/3":8}},"86":{"place":10,"name":"Vojaka 1","organisation_id":1702,"matches":20,"score":19,"counterscore":53,"forfait":0,"points":11,"score_diff":-34,"wins":3,"loss":17,"score_divided":"0,36","ties":0,"custom_results":{"3\/0":1,"3\/1":2,"3\/2":0,"2\/3":2,"1\/3":6,"0\/3":9}},"85":{"place":11,"name":"TESLA Lint VC 1","organisation_id":1703,"matches":20,"score":17,"counterscore":53,"forfait":1,"points":9,"score_diff":-36,"wins":3,"loss":17,"score_divided":"0,32","ties":0,"custom_results":{"3\/0":2,"3\/1":0,"3\/2":1,"2\/3":2,"1\/3":4,"0\/3":11}}},"name":"DAMES 2","type":"league"},"D3A":{"standing":{"99":{"place":1,"name":"Vos Reinaert 2","organisation_id":1568,"matches":22,"score":65,"counterscore":13,"forfait":0,"points":61,"score_diff":52,"wins":21,"loss":1,"score_divided":"5,00","ties":0,"custom_results":{"3\/0":14,"3\/1":4,"3\/2":3,"2\/3":1,"1\/3":0,"0\/3":0}},"98":{"place":2,"name":"Volmar Ekeren 2","organisation_id":1855,"matches":22,"score":53,"counterscore":31,"forfait":0,"points":44,"score_diff":22,"wins":15,"loss":7,"score_divided":"1,71","ties":0,"custom_results":{"3\/0":8,"3\/1":4,"3\/2":3,"2\/3":2,"1\/3":4,"0\/3":1}},"100":{"place":3,"name":"WEK Loenhout 1","organisation_id":1708,"matches":22,"score":50,"counterscore":34,"forfait":0,"points":42,"score_diff":16,"wins":14,"loss":8,"score_divided":"1,47","ties":0,"custom_results":{"3\/0":7,"3\/1":4,"3\/2":3,"2\/3":3,"1\/3":2,"0\/3":3}},"92":{"place":4,"name":"Kokaz 2","organisation_id":1673,"matches":22,"score":50,"counterscore":38,"forfait":0,"points":40,"score_diff":12,"wins":14,"loss":8,"score_divided":"1,32","ties":0,"custom_results":{"3\/0":5,"3\/1":4,"3\/2":5,"2\/3":3,"1\/3":2,"0\/3":3}},"96":{"place":5,"name":"Nidavoc","organisation_id":1566,"matches":22,"score":39,"counterscore":40,"forfait":0,"points":34,"score_diff":-1,"wins":12,"loss":10,"score_divided":"0,98","ties":0,"custom_results":{"3\/0":4,"3\/1":6,"3\/2":2,"2\/3":0,"1\/3":3,"0\/3":7}},"90":{"place":6,"name":"Bovok 1","organisation_id":1658,"matches":22,"score":41,"counterscore":38,"forfait":0,"points":34,"score_diff":3,"wins":11,"loss":11,"score_divided":"1,08","ties":0,"custom_results":{"3\/0":7,"3\/1":3,"3\/2":1,"2\/3":2,"1\/3":4,"0\/3":5}},"91":{"place":7,"name":"Bravoc Ranst 1","organisation_id":1659,"matches":22,"score":44,"counterscore":43,"forfait":0,"points":33,"score_diff":1,"wins":9,"loss":13,"score_divided":"1,02","ties":0,"custom_results":{"3\/0":6,"3\/1":2,"3\/2":1,"2\/3":7,"1\/3":3,"0\/3":3}},"95":{"place":8,"name":"Mortsel Volley Antw 2","organisation_id":1680,"matches":22,"score":41,"counterscore":45,"forfait":2,"points":30,"score_diff":-4,"wins":12,"loss":10,"score_divided":"0,91","ties":0,"custom_results":{"3\/0":2,"3\/1":5,"3\/2":5,"2\/3":1,"1\/3":3,"0\/3":6}},"101":{"place":9,"name":"Woka 2","organisation_id":1709,"matches":22,"score":35,"counterscore":51,"forfait":0,"points":23,"score_diff":-16,"wins":8,"loss":14,"score_divided":"0,69","ties":0,"custom_results":{"3\/0":2,"3\/1":3,"3\/2":3,"2\/3":2,"1\/3":7,"0\/3":5}},"93":{"place":10,"name":"Komart 1","organisation_id":1674,"matches":22,"score":31,"counterscore":51,"forfait":0,"points":22,"score_diff":-20,"wins":7,"loss":15,"score_divided":"0,61","ties":0,"custom_results":{"3\/0":3,"3\/1":2,"3\/2":2,"2\/3":3,"1\/3":4,"0\/3":8}},"97":{"place":11,"name":"Sveka Schoten 3","organisation_id":1696,"matches":22,"score":34,"counterscore":54,"forfait":0,"points":21,"score_diff":-20,"wins":6,"loss":16,"score_divided":"0,63","ties":0,"custom_results":{"3\/0":2,"3\/1":2,"3\/2":2,"2\/3":5,"1\/3":6,"0\/3":5}},"94":{"place":12,"name":"Meilsen","organisation_id":1565,"matches":22,"score":16,"counterscore":61,"forfait":0,"points":10,"score_diff":-45,"wins":3,"loss":19,"score_divided":"0,26","ties":0,"custom_results":{"3\/0":0,"3\/1":2,"3\/2":1,"2\/3":2,"1\/3":3,"0\/3":14}}},"name":"DAMES 3A","type":"league"},"D3B":{"standing":{"103":{"place":1,"name":"AVO Melsele 1","organisation_id":2079,"matches":22,"score":64,"counterscore":15,"forfait":0,"points":62,"score_diff":49,"wins":20,"loss":2,"score_divided":"4,27","ties":0,"custom_results":{"3\/0":11,"3\/1":9,"3\/2":0,"2\/3":2,"1\/3":0,"0\/3":0}},"109":{"place":2,"name":"Hellvoc","organisation_id":1691,"matches":22,"score":60,"counterscore":18,"forfait":0,"points":56,"score_diff":42,"wins":19,"loss":3,"score_divided":"3,33","ties":0,"custom_results":{"3\/0":12,"3\/1":5,"3\/2":2,"2\/3":1,"1\/3":1,"0\/3":1}},"106":{"place":3,"name":"Cantincrode","organisation_id":1660,"matches":22,"score":47,"counterscore":40,"forfait":0,"points":37,"score_diff":7,"wins":11,"loss":11,"score_divided":"1,18","ties":0,"custom_results":{"3\/0":5,"3\/1":5,"3\/2":1,"2\/3":5,"1\/3":4,"0\/3":2}},"102":{"place":4,"name":"Asterix Kieldrecht","organisation_id":1561,"matches":22,"score":47,"counterscore":40,"forfait":0,"points":36,"score_diff":7,"wins":12,"loss":10,"score_divided":"1,18","ties":0,"custom_results":{"3\/0":5,"3\/1":4,"3\/2":3,"2\/3":3,"1\/3":5,"0\/3":2}},"104":{"place":5,"name":"Bovo 1","organisation_id":1657,"matches":22,"score":44,"counterscore":44,"forfait":0,"points":32,"score_diff":0,"wins":12,"loss":10,"score_divided":"1,00","ties":0,"custom_results":{"3\/0":3,"3\/1":4,"3\/2":5,"2\/3":1,"1\/3":6,"0\/3":3}},"107":{"place":6,"name":"Cavavo","organisation_id":1744,"matches":22,"score":41,"counterscore":42,"forfait":0,"points":31,"score_diff":-1,"wins":10,"loss":12,"score_divided":"0,98","ties":0,"custom_results":{"3\/0":6,"3\/1":2,"3\/2":2,"2\/3":3,"1\/3":5,"0\/3":4}},"105":{"place":7,"name":"Bovok 2","organisation_id":1658,"matches":22,"score":36,"counterscore":46,"forfait":0,"points":28,"score_diff":-10,"wins":10,"loss":12,"score_divided":"0,78","ties":0,"custom_results":{"3\/0":4,"3\/1":2,"3\/2":4,"2\/3":2,"1\/3":2,"0\/3":8}},"111":{"place":8,"name":"Komart 2","organisation_id":1674,"matches":22,"score":40,"counterscore":49,"forfait":0,"points":28,"score_diff":-9,"wins":9,"loss":13,"score_divided":"0,82","ties":0,"custom_results":{"3\/0":2,"3\/1":4,"3\/2":3,"2\/3":4,"1\/3":5,"0\/3":4}},"112":{"place":9,"name":"Sveka Schoten 4","organisation_id":1696,"matches":22,"score":38,"counterscore":47,"forfait":0,"points":27,"score_diff":-9,"wins":10,"loss":12,"score_divided":"0,81","ties":0,"custom_results":{"3\/0":4,"3\/1":1,"3\/2":5,"2\/3":2,"1\/3":4,"0\/3":6}},"108":{"place":10,"name":"Fixit Wuustwezel 2","organisation_id":1663,"matches":22,"score":34,"counterscore":51,"forfait":0,"points":23,"score_diff":-17,"wins":7,"loss":15,"score_divided":"0,67","ties":0,"custom_results":{"3\/0":4,"3\/1":0,"3\/2":3,"2\/3":5,"1\/3":3,"0\/3":7}},"113":{"place":11,"name":"Vos Reinaert 3","organisation_id":1568,"matches":22,"score":31,"counterscore":54,"forfait":0,"points":21,"score_diff":-23,"wins":7,"loss":15,"score_divided":"0,57","ties":0,"custom_results":{"3\/0":1,"3\/1":3,"3\/2":3,"2\/3":3,"1\/3":4,"0\/3":8}},"110":{"place":12,"name":"Kokaz 3","organisation_id":1673,"matches":22,"score":23,"counterscore":59,"forfait":0,"points":15,"score_diff":-36,"wins":5,"loss":17,"score_divided":"0,39","ties":0,"custom_results":{"3\/0":0,"3\/1":2,"3\/2":3,"2\/3":3,"1\/3":2,"0\/3":12}}},"name":"DAMES 3B","type":"league"},"D4A":{"standing":{"114":{"place":1,"name":"AVO Melsele 2","organisation_id":2079,"matches":20,"score":54,"counterscore":22,"forfait":0,"points":49,"score_diff":32,"wins":17,"loss":3,"score_divided":"2,45","ties":0,"custom_results":{"3\/0":7,"3\/1":7,"3\/2":3,"2\/3":1,"1\/3":1,"0\/3":1}},"120":{"place":2,"name":"Volleydots","organisation_id":1745,"matches":20,"score":50,"counterscore":32,"forfait":0,"points":42,"score_diff":18,"wins":15,"loss":5,"score_divided":"1,56","ties":0,"custom_results":{"3\/0":3,"3\/1":7,"3\/2":5,"2\/3":2,"1\/3":1,"0\/3":2}},"115":{"place":3,"name":"JOH Volley","organisation_id":1668,"matches":20,"score":47,"counterscore":36,"forfait":1,"points":36,"score_diff":11,"wins":13,"loss":7,"score_divided":"1,31","ties":0,"custom_results":{"3\/0":3,"3\/1":5,"3\/2":5,"2\/3":3,"1\/3":2,"0\/3":2}},"121":{"place":4,"name":"Volmar Ekeren 3","organisation_id":1855,"matches":20,"score":43,"counterscore":35,"forfait":1,"points":34,"score_diff":8,"wins":10,"loss":10,"score_divided":"1,23","ties":0,"custom_results":{"3\/0":5,"3\/1":5,"3\/2":0,"2\/3":5,"1\/3":3,"0\/3":2}},"122":{"place":5,"name":"Vos Reinaert 4","organisation_id":1568,"matches":20,"score":42,"counterscore":34,"forfait":1,"points":32,"score_diff":8,"wins":12,"loss":8,"score_divided":"1,24","ties":0,"custom_results":{"3\/0":5,"3\/1":4,"3\/2":3,"2\/3":0,"1\/3":6,"0\/3":2}},"117":{"place":6,"name":"Kokaz 4","organisation_id":1673,"matches":20,"score":38,"counterscore":40,"forfait":0,"points":30,"score_diff":-2,"wins":10,"loss":10,"score_divided":"0,95","ties":0,"custom_results":{"3\/0":2,"3\/1":6,"3\/2":2,"2\/3":2,"1\/3":4,"0\/3":4}},"124":{"place":7,"name":"Wemmenem","organisation_id":1570,"matches":20,"score":37,"counterscore":36,"forfait":0,"points":29,"score_diff":1,"wins":9,"loss":11,"score_divided":"1,03","ties":0,"custom_results":{"3\/0":7,"3\/1":1,"3\/2":1,"2\/3":3,"1\/3":4,"0\/3":4}},"118":{"place":8,"name":"t Pleintje","organisation_id":1697,"matches":20,"score":33,"counterscore":48,"forfait":0,"points":21,"score_diff":-15,"wins":6,"loss":14,"score_divided":"0,69","ties":0,"custom_results":{"3\/0":1,"3\/1":4,"3\/2":1,"2\/3":4,"1\/3":7,"0\/3":3}},"119":{"place":9,"name":"Vojaka 2","organisation_id":1702,"matches":20,"score":28,"counterscore":47,"forfait":0,"points":20,"score_diff":-19,"wins":7,"loss":13,"score_divided":"0,60","ties":0,"custom_results":{"3\/0":1,"3\/1":4,"3\/2":2,"2\/3":1,"1\/3":5,"0\/3":7}},"123":{"place":10,"name":"Vosco 2","organisation_id":1706,"matches":20,"score":31,"counterscore":48,"forfait":0,"points":19,"score_diff":-17,"wins":7,"loss":13,"score_divided":"0,65","ties":0,"custom_results":{"3\/0":2,"3\/1":1,"3\/2":4,"2\/3":2,"1\/3":6,"0\/3":5}},"116":{"place":11,"name":"Kadee Bornem","organisation_id":1671,"matches":20,"score":26,"counterscore":51,"forfait":0,"points":15,"score_diff":-25,"wins":4,"loss":16,"score_divided":"0,51","ties":0,"custom_results":{"3\/0":1,"3\/1":3,"3\/2":0,"2\/3":3,"1\/3":8,"0\/3":5}}},"name":"DAMES 4A","type":"league"},"D4B":{"standing":{"126":{"place":1,"name":"Dosko@Ristorno 1","organisation_id":1662,"matches":20,"score":60,"counterscore":19,"forfait":0,"points":54,"score_diff":41,"wins":20,"loss":0,"score_divided":"3,16","ties":0,"custom_results":{"3\/0":7,"3\/1":7,"3\/2":6,"2\/3":0,"1\/3":0,"0\/3":0}},"128":{"place":2,"name":"Kokaz 5","organisation_id":1673,"matches":20,"score":51,"counterscore":27,"forfait":0,"points":44,"score_diff":24,"wins":15,"loss":5,"score_divided":"1,89","ties":0,"custom_results":{"3\/0":6,"3\/1":6,"3\/2":3,"2\/3":2,"1\/3":2,"0\/3":1}},"132":{"place":3,"name":"Simikos","organisation_id":1692,"matches":20,"score":46,"counterscore":33,"forfait":0,"points":39,"score_diff":13,"wins":11,"loss":9,"score_divided":"1,39","ties":0,"custom_results":{"3\/0":5,"3\/1":6,"3\/2":0,"2\/3":6,"1\/3":1,"0\/3":2}},"130":{"place":4,"name":"Oxaco BVC Antw 1","organisation_id":1687,"matches":20,"score":44,"counterscore":28,"forfait":0,"points":37,"score_diff":16,"wins":12,"loss":8,"score_divided":"1,57","ties":0,"custom_results":{"3\/0":9,"3\/1":2,"3\/2":1,"2\/3":2,"1\/3":4,"0\/3":2}},"125":{"place":5,"name":"Bravoc Ranst 2","organisation_id":1659,"matches":20,"score":46,"counterscore":36,"forfait":0,"points":36,"score_diff":10,"wins":12,"loss":8,"score_divided":"1,28","ties":0,"custom_results":{"3\/0":4,"3\/1":4,"3\/2":4,"2\/3":4,"1\/3":2,"0\/3":2}},"133":{"place":6,"name":"Sloep VC 2","organisation_id":1694,"matches":20,"score":43,"counterscore":39,"forfait":0,"points":33,"score_diff":4,"wins":11,"loss":9,"score_divided":"1,10","ties":0,"custom_results":{"3\/0":3,"3\/1":4,"3\/2":4,"2\/3":4,"1\/3":2,"0\/3":3}},"127":{"place":7,"name":"Fixit Wuustwezel 3","organisation_id":1663,"matches":20,"score":39,"counterscore":38,"forfait":1,"points":30,"score_diff":1,"wins":10,"loss":10,"score_divided":"1,03","ties":0,"custom_results":{"3\/0":4,"3\/1":4,"3\/2":2,"2\/3":3,"1\/3":3,"0\/3":4}},"135":{"place":8,"name":"WEK Loenhout 2","organisation_id":1708,"matches":20,"score":33,"counterscore":44,"forfait":0,"points":22,"score_diff":-11,"wins":8,"loss":12,"score_divided":"0,75","ties":0,"custom_results":{"3\/0":3,"3\/1":2,"3\/2":3,"2\/3":1,"1\/3":7,"0\/3":4}},"129":{"place":9,"name":"Osta Berchem 1","organisation_id":1684,"matches":20,"score":32,"counterscore":50,"forfait":0,"points":18,"score_diff":-18,"wins":7,"loss":13,"score_divided":"0,64","ties":0,"custom_results":{"3\/0":1,"3\/1":1,"3\/2":5,"2\/3":2,"1\/3":7,"0\/3":4}},"131":{"place":10,"name":"Pannenhuiseke VK","organisation_id":1846,"matches":20,"score":22,"counterscore":53,"forfait":0,"points":12,"score_diff":-31,"wins":3,"loss":17,"score_divided":"0,42","ties":0,"custom_results":{"3\/0":1,"3\/1":2,"3\/2":0,"2\/3":3,"1\/3":7,"0\/3":7}},"134":{"place":11,"name":"Sveka Schoten 5","organisation_id":1696,"matches":20,"score":10,"counterscore":59,"forfait":0,"points":4,"score_diff":-49,"wins":1,"loss":19,"score_divided":"0,17","ties":0,"custom_results":{"3\/0":0,"3\/1":0,"3\/2":1,"2\/3":2,"1\/3":3,"0\/3":14}}},"name":"DAMES 4B","type":"league"},"D5A":{"standing":{"142":{"place":1,"name":"Oxaco BVC Antw 2","organisation_id":1687,"matches":22,"score":63,"counterscore":18,"forfait":0,"points":58,"score_diff":45,"wins":20,"loss":2,"score_divided":"3,50","ties":0,"custom_results":{"3\/0":11,"3\/1":6,"3\/2":3,"2\/3":1,"1\/3":1,"0\/3":0}},"140":{"place":2,"name":"Mavoc Mechelen","organisation_id":1677,"matches":22,"score":61,"counterscore":15,"forfait":0,"points":56,"score_diff":46,"wins":19,"loss":3,"score_divided":"4,07","ties":0,"custom_results":{"3\/0":15,"3\/1":2,"3\/2":2,"2\/3":1,"1\/3":2,"0\/3":0}},"137":{"place":3,"name":"Geel-Zwart Wijnegem 2","organisation_id":1664,"matches":22,"score":61,"counterscore":21,"forfait":0,"points":54,"score_diff":40,"wins":19,"loss":3,"score_divided":"2,90","ties":0,"custom_results":{"3\/0":11,"3\/1":4,"3\/2":4,"2\/3":1,"1\/3":2,"0\/3":0}},"141":{"place":4,"name":"Osta Berchem 2","organisation_id":1684,"matches":22,"score":56,"counterscore":26,"forfait":0,"points":49,"score_diff":30,"wins":16,"loss":6,"score_divided":"2,15","ties":0,"custom_results":{"3\/0":9,"3\/1":6,"3\/2":1,"2\/3":2,"1\/3":4,"0\/3":0}},"139":{"place":5,"name":"Jong Edegem 2","organisation_id":1670,"matches":22,"score":48,"counterscore":33,"forfait":0,"points":41,"score_diff":15,"wins":13,"loss":9,"score_divided":"1,45","ties":0,"custom_results":{"3\/0":8,"3\/1":4,"3\/2":1,"2\/3":3,"1\/3":3,"0\/3":3}},"138":{"place":6,"name":"Joledi","organisation_id":1669,"matches":22,"score":42,"counterscore":37,"forfait":1,"points":36,"score_diff":5,"wins":12,"loss":10,"score_divided":"1,14","ties":0,"custom_results":{"3\/0":6,"3\/1":5,"3\/2":1,"2\/3":2,"1\/3":2,"0\/3":6}},"145":{"place":7,"name":"Volley Niel 1","organisation_id":1704,"matches":22,"score":37,"counterscore":41,"forfait":0,"points":29,"score_diff":-4,"wins":10,"loss":12,"score_divided":"0,90","ties":0,"custom_results":{"3\/0":7,"3\/1":1,"3\/2":2,"2\/3":1,"1\/3":5,"0\/3":6}},"144":{"place":8,"name":"TESLA Lint VC 2","organisation_id":1703,"matches":22,"score":38,"counterscore":41,"forfait":1,"points":28,"score_diff":-3,"wins":9,"loss":13,"score_divided":"0,93","ties":0,"custom_results":{"3\/0":7,"3\/1":2,"3\/2":0,"2\/3":2,"1\/3":7,"0\/3":4}},"143":{"place":9,"name":"Racing Deurne OB","organisation_id":1689,"matches":22,"score":21,"counterscore":50,"forfait":0,"points":18,"score_diff":-29,"wins":6,"loss":16,"score_divided":"0,42","ties":0,"custom_results":{"3\/0":4,"3\/1":2,"3\/2":0,"2\/3":0,"1\/3":3,"0\/3":13}},"136":{"place":10,"name":"Bovo 2","organisation_id":1657,"matches":22,"score":19,"counterscore":52,"forfait":5,"points":11,"score_diff":-33,"wins":5,"loss":17,"score_divided":"0,37","ties":0,"custom_results":{"3\/0":4,"3\/1":1,"3\/2":0,"2\/3":1,"1\/3":2,"0\/3":14}},"146":{"place":11,"name":"Woka 3","organisation_id":1709,"matches":22,"score":9,"counterscore":61,"forfait":0,"points":6,"score_diff":-52,"wins":2,"loss":20,"score_divided":"0,15","ties":0,"custom_results":{"3\/0":1,"3\/1":1,"3\/2":0,"2\/3":0,"1\/3":3,"0\/3":17}},"147":{"place":12,"name":"Komart 3","organisation_id":1674,"matches":22,"score":4,"counterscore":64,"forfait":0,"points":3,"score_diff":-60,"wins":1,"loss":21,"score_divided":"0,06","ties":0,"custom_results":{"3\/0":0,"3\/1":1,"3\/2":0,"2\/3":0,"1\/3":1,"0\/3":20}}},"name":"DAMES 5A","type":"league"},"D5B":{"standing":{"156":{"place":1,"name":"Volley Niel 2","organisation_id":1704,"matches":20,"score":56,"counterscore":7,"forfait":0,"points":55,"score_diff":49,"wins":18,"loss":2,"score_divided":"8,00","ties":0,"custom_results":{"3\/0":17,"3\/1":1,"3\/2":0,"2\/3":1,"1\/3":0,"0\/3":1}},"157":{"place":2,"name":"VOS Schilde","organisation_id":1698,"matches":20,"score":56,"counterscore":16,"forfait":0,"points":52,"score_diff":40,"wins":18,"loss":2,"score_divided":"3,50","ties":0,"custom_results":{"3\/0":11,"3\/1":4,"3\/2":3,"2\/3":1,"1\/3":0,"0\/3":1}},"154":{"place":3,"name":"Oxaco BVC Antw 3","organisation_id":1687,"matches":20,"score":50,"counterscore":19,"forfait":0,"points":45,"score_diff":31,"wins":14,"loss":6,"score_divided":"2,63","ties":0,"custom_results":{"3\/0":13,"3\/1":1,"3\/2":0,"2\/3":3,"1\/3":2,"0\/3":1}},"152":{"place":4,"name":"Jong Edegem 3","organisation_id":1670,"matches":20,"score":45,"counterscore":23,"forfait":0,"points":41,"score_diff":22,"wins":14,"loss":6,"score_divided":"1,96","ties":0,"custom_results":{"3\/0":10,"3\/1":3,"3\/2":1,"2\/3":0,"1\/3":3,"0\/3":3}},"150":{"place":5,"name":"Fixit Wuustwezel 4","organisation_id":1663,"matches":20,"score":43,"counterscore":28,"forfait":0,"points":39,"score_diff":15,"wins":14,"loss":6,"score_divided":"1,54","ties":0,"custom_results":{"3\/0":7,"3\/1":4,"3\/2":3,"2\/3":0,"1\/3":1,"0\/3":5}},"158":{"place":6,"name":"WEK Loenhout 3","organisation_id":1708,"matches":20,"score":30,"counterscore":35,"forfait":0,"points":27,"score_diff":-5,"wins":9,"loss":11,"score_divided":"0,86","ties":0,"custom_results":{"3\/0":8,"3\/1":0,"3\/2":1,"2\/3":1,"1\/3":1,"0\/3":9}},"149":{"place":7,"name":"Dosko@Ristorno 2","organisation_id":1662,"matches":20,"score":30,"counterscore":39,"forfait":0,"points":25,"score_diff":-9,"wins":8,"loss":12,"score_divided":"0,77","ties":0,"custom_results":{"3\/0":6,"3\/1":1,"3\/2":1,"2\/3":2,"1\/3":2,"0\/3":8}},"151":{"place":8,"name":"Geel-Zwart Wijnegem 3","organisation_id":1664,"matches":20,"score":26,"counterscore":46,"forfait":0,"points":19,"score_diff":-20,"wins":6,"loss":14,"score_divided":"0,57","ties":0,"custom_results":{"3\/0":4,"3\/1":0,"3\/2":2,"2\/3":3,"1\/3":2,"0\/3":9}},"148":{"place":9,"name":"Okee VC","organisation_id":1683,"matches":20,"score":21,"counterscore":47,"forfait":0,"points":17,"score_diff":-26,"wins":6,"loss":14,"score_divided":"0,45","ties":0,"custom_results":{"3\/0":2,"3\/1":3,"3\/2":1,"2\/3":0,"1\/3":3,"0\/3":11}},"153":{"place":10,"name":"Osta Berchem 3","organisation_id":1684,"matches":20,"score":14,"counterscore":51,"forfait":1,"points":9,"score_diff":-37,"wins":3,"loss":17,"score_divided":"0,27","ties":0,"custom_results":{"3\/0":3,"3\/1":0,"3\/2":0,"2\/3":1,"1\/3":3,"0\/3":13}},"155":{"place":11,"name":"Sveka Schoten 6","organisation_id":1696,"matches":20,"score":0,"counterscore":60,"forfait":0,"points":0,"score_diff":-60,"wins":0,"loss":20,"score_divided":"0,00","ties":0,"custom_results":{"3\/0":0,"3\/1":0,"3\/2":0,"2\/3":0,"1\/3":0,"0\/3":20}}},"name":"DAMES 5B","type":"league"}}